{
  "id": "I0WbKa5S0J2s5Rs",
  "unique_key": "https://www.nike.com/sg/t/giannis-immortality-4-younger-shoes-c3dxgr/fz6733-501",
  "order_no": "1750343599199.256000",
  "handled_at": null,
  "request": {
    "url": "https://www.nike.com/sg/t/giannis-immortality-4-younger-shoes-C3dxgr/FZ6733-501",
    "method": "GET",
    "headers": {},
    "payload": null,
    "user_data": {
      "__crawlee": {
        "crawlDepth": 2
      },
      "label": "detail"
    },
    "retry_count": 0,
    "no_retry": false,
    "loaded_url": null,
    "handled_at": null,
    "unique_key": "https://www.nike.com/sg/t/giannis-immortality-4-younger-shoes-c3dxgr/fz6733-501",
    "id": "I0WbKa5S0J2s5Rs"
  }
}